python_package_sync_tool-0.5.3-py3.8-nspkg.pth
alexber/reqsync/__init__.py
alexber/reqsync/app.py
alexber/reqsync/data/__init__.py
alexber/reqsync/data/__main__.py
alexber/reqsync/data/config.yml
alexber/reqsync/data/requirements-dest.txt
alexber/reqsync/data/requirements-src.txt
alexber/reqsync/utils/__init__.py
data/__init__.py
data/__main__.py
python_package_sync_tool-0.5.3.dist-info/LICENSE.txt
python_package_sync_tool-0.5.3.dist-info/METADATA
python_package_sync_tool-0.5.3.dist-info/WHEEL
python_package_sync_tool-0.5.3.dist-info/entry_points.txt
python_package_sync_tool-0.5.3.dist-info/namespace_packages.txt
python_package_sync_tool-0.5.3.dist-info/top_level.txt
python_package_sync_tool-0.5.3.dist-info/RECORD
