Metadata-Version: 2.1
Name: python-package-sync-tool
Version: 0.5.3
Summary: Small tool to sync package from different machines
Home-page: https://github.com/alex-ber/PythonPackageSyncTool
Author: Alexander Berkovich
License: Apache 2.0
Keywords: tools tool sync package pip
Platform: UNKNOWN
Classifier: Development Status :: 3 - Alpha
Classifier: Environment :: Console
Classifier: Intended Audience :: Developers
Classifier: Intended Audience :: Education
Classifier: License :: OSI Approved :: BSD License
Classifier: Programming Language :: Python
Classifier: Programming Language :: Python :: 3 :: Only
Classifier: Programming Language :: Python :: 3.7
Classifier: Programming Language :: Python :: 3.8
Classifier: Programming Language :: Python :: Implementation :: CPython
Classifier: Topic :: Utilities
Classifier: Topic :: Software Development :: Libraries :: Python Modules
Classifier: Topic :: Desktop Environment
Classifier: Topic :: Education
Classifier: Operating System :: OS Independent
Classifier: Operating System :: Microsoft :: Windows
Classifier: Operating System :: POSIX
Classifier: Operating System :: Unix
Classifier: Natural Language :: English
Requires-Python: >=3.7.1
Requires-Dist: alex-ber-utils (==0.6.2)
Requires-Dist: alex-ber-utils[yml] (==0.6.2)
Provides-Extra: tests
Requires-Dist: attrs (==20.2.0) ; extra == 'tests'
Requires-Dist: mock (==4.0.2) ; extra == 'tests'
Requires-Dist: py (==1.9.0) ; extra == 'tests'
Requires-Dist: pytest (==6.1.2) ; extra == 'tests'
Requires-Dist: pytest-assume (==2.3.3) ; extra == 'tests'
Requires-Dist: pytest-mock (==3.3.1) ; extra == 'tests'
Requires-Dist: PyYAML (==5.1) ; extra == 'tests'
Requires-Dist: toml (==0.10.2) ; extra == 'tests'
Requires-Dist: pluggy (==0.13.1) ; extra == 'tests'
Requires-Dist: packaging (==20.4) ; extra == 'tests'
Requires-Dist: iniconfig (==1.1.1) ; extra == 'tests'
Requires-Dist: pyparsing (==2.4.7) ; extra == 'tests'
